usbguard_simple_gui_py_qt/__init__.py
usbguard_simple_gui_py_qt/device.py
usbguard_simple_gui_py_qt/icon.svg
usbguard_simple_gui_py_qt/main_window.py
usbguard_simple_gui_py_qt/rule_parsing.py
usbguard_simple_gui_py_qt/rules.py
usbguard_simple_gui_py_qt/system_tray_app.py
usbguard_simple_gui_py_qt/usbguard_dbus_interface.py
usbguard_simple_gui_py_qt-0.0.1.dist-info/LICENSE
usbguard_simple_gui_py_qt-0.0.1.dist-info/METADATA
usbguard_simple_gui_py_qt-0.0.1.dist-info/WHEEL
usbguard_simple_gui_py_qt-0.0.1.dist-info/entry_points.txt
usbguard_simple_gui_py_qt-0.0.1.dist-info/top_level.txt
usbguard_simple_gui_py_qt-0.0.1.dist-info/RECORD
